Metadata-Version: 2.1
Name: pulumi-aws-miniflux
Version: 0.1.0
Summary: UNKNOWN
Home-page: UNKNOWN
License: UNKNOWN
Platform: UNKNOWN
